Metadata-Version: 2.1
Name: kedro-serving
Version: 0.0.1
Summary: A kedro plugin to serve kedro pipelines
Home-page: https://github.com/Galileo-Galilei/kedro-serving
Author: Yolan Honoré-Rougé
License: Apache Software License (Apache 2.0)
Platform: UNKNOWN
Classifier: Development Status :: 4 - Beta
Classifier: Programming Language :: Python :: 3.6
Classifier: Programming Language :: Python :: 3.7
Classifier: Programming Language :: Python :: 3.8
Requires-Python: >=3.6, <3.9
Provides-Extra: doc
Provides-Extra: test
Provides-Extra: dev
